wavedisp/__init__.py
wavedisp/ast.py
wavedisp/cli.py
wavedisp/visitor.py
wavedisp/targets/__init__.py
wavedisp/targets/gtkwave.py
wavedisp/targets/modelsim.py
wavedisp/targets/rivierapro.py
wavedisp/targets/x11colors.py
wavedisp-1.0.6.dist-info/LICENSE
wavedisp-1.0.6.dist-info/METADATA
wavedisp-1.0.6.dist-info/WHEEL
wavedisp-1.0.6.dist-info/entry_points.txt
wavedisp-1.0.6.dist-info/top_level.txt
wavedisp-1.0.6.dist-info/RECORD
